FyeldGenerator/__init__.py
FyeldGenerator/core.py
FyeldGenerator-0.1.7.dist-info/LICENSE
FyeldGenerator-0.1.7.dist-info/METADATA
FyeldGenerator-0.1.7.dist-info/WHEEL
FyeldGenerator-0.1.7.dist-info/top_level.txt
FyeldGenerator-0.1.7.dist-info/RECORD
