Metadata-Version: 2.1
Name: FyeldGenerator
Version: 0.1.7
Summary: Simple package to symmetric generate random field.
Home-page: https://github.com/cphyc/FyeldGenerator
Author: Corentin Cadiou
Author-email: contact@cphyc.me
License: CC-BY-SA2.0
Platform: UNKNOWN
Classifier: Development Status :: 3 - Alpha
Classifier: License :: Free To Use But Restricted
Classifier: Programming Language :: Python
Classifier: Programming Language :: Python :: 3 :: Only
Classifier: Topic :: Scientific/Engineering
License-File: LICENSE
Requires-Dist: numpy
